AUTHORS.rst
CONTRIBUTING.rst
HISTORY.rst
LICENSE
MANIFEST.in
README.rst
setup.cfg
setup.py
docs/Makefile
docs/authors.rst
docs/conf.py
docs/contributing.rst
docs/history.rst
docs/index.rst
docs/installation.rst
docs/make.bat
docs/readme.rst
docs/usage.rst
tests/__init__.py
tests/test_walker.py
walker/__init__.py
walker/main.py
walker.egg-info/PKG-INFO
walker.egg-info/SOURCES.txt
walker.egg-info/dependency_links.txt
walker.egg-info/entry_points.txt
walker.egg-info/not-zip-safe
walker.egg-info/top_level.txt