Metadata-Version: 1.1
Name: walker
Version: 0.0.1
Summary: Walker executes the same command on multiple directories.
Home-page: https://github.com/darylyu/walker
Author: D. Yu
Author-email: dyu+honeypot@fastmail.fm
License: BSD
Keywords: walker
Platform: UNKNOWN
Classifier: Development Status :: 2 - Pre-Alpha
Classifier: Intended Audience :: Developers
Classifier: License :: OSI Approved :: BSD License
Classifier: Natural Language :: English
Classifier: Programming Language :: Python :: 2
Classifier: Programming Language :: Python :: 2.6
Classifier: Programming Language :: Python :: 2.7
Classifier: Programming Language :: Python :: 3
Classifier: Programming Language :: Python :: 3.3
Classifier: Programming Language :: Python :: 3.4
